LICENSE
MANIFEST.in
README.md
setup.py
django_imguploder/.DS_Store
django_imguploder/__init__.py
django_imguploder/admin.py
django_imguploder/apps.py
django_imguploder/models.py
django_imguploder/tests.py
django_imguploder/views.py
django_imguploder/forms/__init__.py
django_imguploder/forms/widget.py
django_imguploder/migrations/__init__.py
django_imguploder/static/.DS_Store
django_imguploder/static/admin/css/imgwidget.css
django_imguploder/static/admin/css/viewer.css
django_imguploder/static/admin/js/img_multi_upload.js
django_imguploder/static/admin/js/jquery.min.js
django_imguploder/static/admin/js/viewer.min.js
django_imguploder/templates/.DS_Store
django_imguploder/templates/admin/widgets/img_multi_upload.html
django_imgwidget.egg-info/PKG-INFO
django_imgwidget.egg-info/SOURCES.txt
django_imgwidget.egg-info/dependency_links.txt
django_imgwidget.egg-info/not-zip-safe
django_imgwidget.egg-info/requires.txt
django_imgwidget.egg-info/top_level.txt