Metadata-Version: 2.1
Name: django-imgwidget
Version: 0.0.6
Summary: 上传图片组件
Home-page: https://github.com/RelaxedDong/django_imguploder
Author: donghao
Author-email: 1417766861@qq.com
License: Apache License 2.0
Keywords: django,admin,widget,image,uploader
Classifier: Programming Language :: Python :: 3
Classifier: Operating System :: OS Independent
License-File: LICENSE
